<?xml version="1.0" encoding="UTF-8"?>
<Document>
    <Order OrderDate = "2006-6-6">
        <Customer Name = "Helen Mooney">
            <ProductOne ProductID = "2" Quantity = "2" />
            <ProductTow ProductID = "4" Quantity = "4" />
        </Customer>
    </Order>
    <Catalog>
        <CatagoryOne Name = "Beverages">
            <Product ID = "1" Name = "Coca-cola"/>
        </CatagoryOne>
        <CatogoryTow Name = "Furiture">
            <ProductOne ID = "2" Name = "Chair" />
            <ProductTow ID = "2" Name = "Desk" />
        </CatogoryTow>
    </Catalog>
</Document>
